quits/circuit.py
quits/decoder.py
quits/gf2_util.py
quits/ldpc_util.py
quits/qldpc_code.py
quits/simulation.py
quits-0.4.1.dist-info/licenses/LICENSE
quits-0.4.1.dist-info/METADATA
quits-0.4.1.dist-info/WHEEL
quits-0.4.1.dist-info/top_level.txt
quits-0.4.1.dist-info/RECORD
