Metadata-Version: 2.4
Name: quits
Version: 0.4.1
Summary: A modular Qldpc code circUIT Simulator
Author-email: Mingyu Kang <mingyu.kang@duke.edu>, Yingjia Lin <yingjia.lin@duke.edu>, Hanwen Yao <hanwen.yao@duke.edu>, Mert Gökduman <mert.gokduman@duke.edu>
License: MIT License
Project-URL: Homepage, https://github.com/mkangquantum/quits.git
Classifier: Programming Language :: Python :: 3
Classifier: Operating System :: OS Independent
Requires-Python: >=3.9.7
License-File: LICENSE
Requires-Dist: numpy>=1.24.0
Requires-Dist: scipy>=1.9.3
Requires-Dist: matplotlib
Requires-Dist: stim>=1.13.0
Requires-Dist: networkx>=2.8.8
Requires-Dist: ldpc>=2.1.2
Dynamic: license-file
